batch_integrated_gradients/batch_integrated_gradients.py
batch_integrated_gradients-1.0.0.dist-info/METADATA
batch_integrated_gradients-1.0.0.dist-info/WHEEL
batch_integrated_gradients-1.0.0.dist-info/top_level.txt
batch_integrated_gradients-1.0.0.dist-info/RECORD
